shipyard_looker/__init__.py
shipyard_looker/cli/authtest.py
shipyard_looker/cli/create_sql_query.py
shipyard_looker/cli/download_dashboard.py
shipyard_looker/cli/download_look_as_file.py
shipyard_looker/cli/run_sql_query.py
shipyard_looker/exceptions.py
shipyard_looker/looker.py
shipyard_looker-0.2.0.dist-info/METADATA
shipyard_looker-0.2.0.dist-info/WHEEL
shipyard_looker-0.2.0.dist-info/RECORD
