Metadata-Version: 2.1
Name: shipyard-looker
Version: 0.2.0
Summary: A local client for connecting and looking with Looker
License: Apache 2.0
Author: wrp801
Author-email: wespoulsen@gmail.com
Requires-Python: >=3.9,<4.0
Classifier: License :: Other/Proprietary License
Classifier: Programming Language :: Python :: 3
Classifier: Programming Language :: Python :: 3.9
Classifier: Programming Language :: Python :: 3.10
Classifier: Programming Language :: Python :: 3.11
Requires-Dist: looker-sdk (==22.20.0)
Requires-Dist: shipyard-bp-utils (>=1.2.0,<2.0.0)
Requires-Dist: shipyard-templates (==0.8.0)
Requires-Dist: shipyard-utils (==0.1.4)
